{
  "nodes": [
    {
      "type": "event",
      "name": "User Joins Server",
      "guid": "49ebbc23-2903-4f05-ab69-bc9ecb4f067e",
      "variables": {
        "user": "newuser"
      },
      "outputs": [
        {
          "label": "responses",
          "connections": [
            "297ffc16-6a0c-4331-af95-07be5238cbfd"
          ]
        }
      ],
      "x": 99,
      "y": 100,
      "perms": []
    },
    {
      "type": "event",
      "name": "Any Message",
      "guid": "49ebbc23-2903-4f05-ab69-bc9ecb4f8888",
      "variables": {
        "user": "msguser"
      },
      "outputs": [
        {
          "label": "responses",
          "connections": []
        }
      ],
      "x": 101,
      "y": 499,
      "perms": []
    },
    {
      "type": "event",
      "name": "User Kicked",
      "guid": "69ebbc23-2903-4f05-ab69-bc9ecb4f067e",
      "variables": {
        "user": "kickuser"
      },
      "outputs": [
        {
          "label": "responses",
          "connections": []
        }
      ],
      "x": 99,
      "y": 250,
      "perms": []
    },
    {
      "type": "event",
      "name": "User Banned",
      "guid": "77ebbc23-2003-4f05-ab69-bc9ecb4f067e",
      "variables": {
        "user": "banuser"
      },
      "outputs": [
        {
          "label": "responses",
          "connections": []
        }
      ],
      "x": 100,
      "y": 375,
      "perms": []
    },
    {
      "type": "event",
      "name": "Bot Initialization",
      "guid": "0101bc23-2003-4f05-ab69-bc9ecb4f067e",
      "variables": {},
      "outputs": [
        {
          "label": "responses",
          "connections": []
        }
      ],
      "x": 100,
      "y": 625,
      "perms": []
    },
    {
      "type": "response",
      "name": "Welcome message",
      "guid": "297ffc16-6a0c-4331-af95-07be5238cbfd",
      "reactionFields": [],
      "embedfields": [],
      "saveToVariable": "",
      "saveToVariableType": "temp",
      "outputs": [
        {
          "label": "next response",
          "connections": []
        }
      ],
      "inputs": [
        {
          "label": "trigger",
          "id": "49ebbc23-2903-4f05-ab69-bc9ecb4f067e"
        }
      ],
      "x": 434,
      "y": 92,
      "rtype": "Message",
      "rsubtype": "Send Message",
      "formdata": [
        "${dbsVars.DefaultChannel.id}",
        "Welcome, <@${tempVars.newuser.id}>.",
        "",
        "temp"
      ],
      "formnames": [
        "channelName",
        "messageText",
        "saveToVariable",
        "saveToVariableType"
      ]
    }
  ]
}